decomposition/__init__.py
decomposition/decomposition.py
prtest/__init__.py
prtest/prtest.py
pymueller/__init__.py
pymueller/decomposition.py
pymueller/prtest.py
tests/__init__.py
tests/test_decomposition.py
tests/test_prtest.py
pymueller-0.1.3.dist-info/LICENSE
pymueller-0.1.3.dist-info/METADATA
pymueller-0.1.3.dist-info/WHEEL
pymueller-0.1.3.dist-info/top_level.txt
pymueller-0.1.3.dist-info/RECORD
