Metadata-Version: 2.2
Name: pymueller
Version: 0.1.3
Summary: Tools and functions for 4x4 Mueller matrices
Author: Chae chae
Author-email: a40075@outlook.com
Classifier: Programming Language :: Python :: 3
Classifier: Operating System :: OS Independent
Requires-Python: >=3.6
License-File: LICENSE
Requires-Dist: numpy>=1.20
Requires-Dist: opencv-python>=4.11
Dynamic: author
Dynamic: author-email
Dynamic: classifier
Dynamic: description
Dynamic: description-content-type
Dynamic: requires-dist
Dynamic: requires-python
Dynamic: summary
